MANIFEST.in
README.md
hurr-durr
hurr-durr-convert-file-to-sqlite
setup.py
hurr_durr/__init__.py
hurr_durr/handlers.py
hurr_durr/watcher.py
hurr_durr.egg-info/PKG-INFO
hurr_durr.egg-info/SOURCES.txt
hurr_durr.egg-info/dependency_links.txt
hurr_durr.egg-info/requires.txt
hurr_durr.egg-info/top_level.txt
hurr_durr.egg-info/zip-safe