Metadata-Version: 1.1
Name: hurr-durr
Version: 0.2.2
Summary: Streaming async interface to 4chan boards
Home-page: https://github.com/emilssolmanis/hurr-durr
Author: Emils Solmanis
Author-email: emils.solmanis@gmail.com
License: Apache License (2.0)
Download-URL: https://github.com/emilssolmanis/hurr-durr/archive/0.2.2.tar.gz
Keywords: 4chan stream async
Platform: UNKNOWN
